today/__init__.py
today/plugin.py
mkdocs_today_plugin-0.1.0.dist-info/METADATA
mkdocs_today_plugin-0.1.0.dist-info/WHEEL
mkdocs_today_plugin-0.1.0.dist-info/entry_points.txt
mkdocs_today_plugin-0.1.0.dist-info/RECORD
